<?xml version="1.0" encoding="utf-8" ?>
<dwsync>
<file name="typehead.js" server="www.un.org//en/newtechnologies/" local="131816940000000000" remote="131816940000000000" Dst="1" />
<file name="timepicker.js" server="www.un.org//en/newtechnologies/" local="131816940000000000" remote="131816940000000000" Dst="1" />
<file name="star-rating.js" server="www.un.org//en/newtechnologies/" local="131816940000000000" remote="131816940000000000" Dst="1" />
<file name="selectsplitter.js" server="www.un.org//en/newtechnologies/" local="131816940000000000" remote="131816940000000000" Dst="1" />
<file name="select-boxes.js" server="www.un.org//en/newtechnologies/" local="131816940000000000" remote="131816940000000000" Dst="1" />
<file name="responsive-tabs.js" server="www.un.org//en/newtechnologies/" local="131816940000000000" remote="131816940000000000" Dst="1" />
<file name="rangeslider.min.js" server="www.un.org//en/newtechnologies/" local="131816940000000000" remote="131816940000000000" Dst="1" />
<file name="moment.js" server="www.un.org//en/newtechnologies/" local="131816940000000000" remote="131816940000000000" Dst="1" />
<file name="daterangepicker.js" server="www.un.org//en/newtechnologies/" local="131816940000000000" remote="131816940000000000" Dst="1" />
<file name="datepicker.js" server="www.un.org//en/newtechnologies/" local="131816940000000000" remote="131816940000000000" Dst="1" />
<file name="bs-switches.js" server="www.un.org//en/newtechnologies/" local="131816940000000000" remote="131816940000000000" Dst="1" />
<file name="bs-select.js" server="www.un.org//en/newtechnologies/" local="131816940000000000" remote="131816940000000000" Dst="1" />
<file name="bs-filestyle.js" server="www.un.org//en/newtechnologies/" local="131816940000000000" remote="131816940000000000" Dst="1" />
<file name="bs-datatable.js" server="www.un.org//en/newtechnologies/" local="131816940000000000" remote="131816940000000000" Dst="1" />
</dwsync>